pyasice/__init__.py
pyasice/container.py
pyasice/exceptions.py
pyasice/ocsp.py
pyasice/signature_verifier.py
pyasice/templates/manifest.xml
pyasice/templates/signature.xml
pyasice/tsa.py
pyasice/utils.py
pyasice/xmlsig.py
pyasice-1.2.0.dist-info/LICENSE.md
pyasice-1.2.0.dist-info/METADATA
pyasice-1.2.0.dist-info/WHEEL
pyasice-1.2.0.dist-info/RECORD
