Metadata-Version: 2.1
Name: pyasice
Version: 1.2.0
Summary: Manipulate ASiC-E containers and XAdES/eIDAS signatures for Estonian e-identity services
Home-page: https://github.com/thorgate/pyasice
License: ISC
Keywords: esteid,asice,smartid,mobile-id,idcard
Author: Thorgate
Author-email: info@thorgate.eu
Maintainer: Jyrno Ader
Maintainer-email: jyrno42@gmail.com
Requires-Python: >=3.7,<4.0
Classifier: Development Status :: 5 - Production/Stable
Classifier: Intended Audience :: Developers
Classifier: License :: OSI Approved
Classifier: License :: OSI Approved :: ISC License (ISCL)
Classifier: Natural Language :: English
Classifier: Programming Language :: Python :: 3
Classifier: Programming Language :: Python :: 3.7
Classifier: Programming Language :: Python :: 3.8
Classifier: Programming Language :: Python :: 3.9
Classifier: Programming Language :: Python :: 3.10
Classifier: Programming Language :: Python :: 3.11
Classifier: Programming Language :: Python :: 3.12
Classifier: Programming Language :: Python :: 3.13
Requires-Dist: asn1crypto
Requires-Dist: cryptography (>=5)
Requires-Dist: lxml (>=4,<5)
Requires-Dist: oscrypto
Requires-Dist: requests (>=2.20)
Project-URL: Repository, https://github.com/thorgate/pyasice
